{
    "code":200,
    "msg":"success",
    "newslist":[
        {
            "ctime":"2019-11-15 17:04",
            "title":"HIFIMAN发布新耳机DEVA 售价1780元",
            "description":"网易IT",
            "picUrl":"http://cms-bucket.ws.126.net/2019/11/15/a668a4ca0ec344a2abc527e5e5b6fa69.png?imageView&thumbnail=200y140",
            "url":"https://tech.163.com/19/1115/17/EU1P8N1V00097U7T.html"
        },
        {
            "ctime":"2019-11-15 17:08",
            "title":"任正非:今年公司利润太多了 建议终端公司少赚些",
            "description":"网易IT",
            "picUrl":"http://cms-bucket.ws.126.net/2019/11/15/0a5c58c26b44407f80ff690562fbf4d2.png?imageView&thumbnail=200y140",
            "url":"https://tech.163.com/19/1115/17/EU1PFRJM00097U7T.html"
        },
        {
            "ctime":"2019-11-15 15:34",
            "title":"价格不便宜，但为什么中国消费者这么喜欢戴森？",
            "description":"网易IT",
            "picUrl":"http://cms-bucket.ws.126.net/2019/11/15/7bb207713f7445eda7390f289eb64931.png?imageView&thumbnail=200y140",
            "url":"https://tech.163.com/19/1115/15/EU1K457B00097U7T.html"
        },
        {
            "ctime":"2019-11-15 15:37",
            "title":"对话联想童夫尧:超算+AI+5G将成未来超算研究",
            "description":"网易IT",
            "picUrl":"http://cms-bucket.ws.126.net/2019/11/15/04cbbfa15f834bef904a0e140dae4695.png?imageView&thumbnail=200y140",
            "url":"https://tech.163.com/19/1115/15/EU1K99I200097U7T.html"
        },
        {
            "ctime":"2019-11-15 15:46",
            "title":"特斯拉国产Model3即将交付 订单显示车辆准备交",
            "description":"网易IT",
            "picUrl":"http://cms-bucket.ws.126.net/2019/11/15/b21cc9e068b941a4ba1be9270b08b24a.png?imageView&thumbnail=200y140",
            "url":"https://tech.163.com/19/1115/15/EU1KQ4DQ00097U7T.html"
        },
        {
            "ctime":"2019-11-15 12:01",
            "title":"杨元庆：联想手机业务的第一要务是盈利",
            "description":"网易IT",
            "picUrl":"http://cms-bucket.ws.126.net/2019/11/15/b8cb0a38a3a64bb1808135317ea44c1b.png?imageView&thumbnail=200y140",
            "url":"https://tech.163.com/19/1115/12/EU17UDD700097U7T.html"
        },
        {
            "ctime":"2019-11-15 08:07",
            "title":"微软拟2020年推出游戏流媒体服务XCloud PC也能",
            "description":"网易IT",
            "picUrl":"http://cms-bucket.ws.126.net/2019/11/15/0632fc3d0e214334a5fe4dce8c5db38c.png?imageView&thumbnail=200y140",
            "url":"https://tech.163.com/19/1115/08/EU0QHLQC00097U7T.html"
        },
        {
            "ctime":"2019-11-15 08:33",
            "title":"苹果拟将多项付费服务捆绑订阅 或于2020年推出",
            "description":"网易IT",
            "picUrl":"http://cms-bucket.ws.126.net/2019/11/15/f95af90062a645ccaefdd117054c2073.png?imageView&thumbnail=200y140",
            "url":"https://tech.163.com/19/1115/08/EU0S16K900097U7T.html"
        },
        {
            "ctime":"2019-11-15 07:29",
            "title":"英伟达Q3营收30亿美元 利润9亿美元同比下滑27%",
            "description":"网易IT",
            "picUrl":"http://cms-bucket.ws.126.net/2019/11/15/57980848e6ea4f33b38f89793ea6b905.png?imageView&thumbnail=200y140",
            "url":"https://tech.163.com/19/1115/07/EU0OC77300097U7T.html"
        },
        {
            "ctime":"2019-11-15 07:43",
            "title":"巴菲特三季度减持75万股苹果股票，还剩2.48亿股",
            "description":"网易IT",
            "picUrl":"http://cms-bucket.ws.126.net/2019/11/15/e33d1201515a4a87a129218240862510.png?imageView&thumbnail=200y140",
            "url":"https://tech.163.com/19/1115/07/EU0P5KH400097U7T.html"
        },
        {
            "ctime":"2019-11-15 07:48",
            "title":"不满失去百亿美元合同 传亚马逊向美国防部提抗",
            "description":"网易IT",
            "picUrl":"http://cms-bucket.ws.126.net/2019/11/15/87330fcd6ad143f88c28744bdc561e6b.png?imageView&thumbnail=200y140",
            "url":"https://tech.163.com/19/1115/07/EU0PF1KR00097U7T.html"
        },
        {
            "ctime":"2019-11-14 21:43",
            "title":"小鹏融资、恒大造车，造车新势力的梦还能走多远",
            "description":"网易IT",
            "picUrl":"http://cms-bucket.ws.126.net/2019/11/14/c595bd61ab8e4005b71604dd8870ef13.png?imageView&thumbnail=200y140",
            "url":"https://tech.163.com/19/1114/21/ETVMQQ9400097U7T.html"
        },
        {
            "ctime":"2019-11-14 16:17",
            "title":"杨元庆谈moto折叠手机：我们是发手机不是平板",
            "description":"网易IT",
            "picUrl":"http://cms-bucket.ws.126.net/2019/11/14/5be6d7a2218e4cbcadcf0d2fc8eeab23.png?imageView&thumbnail=200y140",
            "url":"https://tech.163.com/19/1114/16/ETV45V6K00097U7T.html"
        },
        {
            "ctime":"2019-11-14 11:06",
            "title":"特斯拉一度成市值第三大车企：前面仅剩丰田大众",
            "description":"网易IT",
            "picUrl":"http://cms-bucket.ws.126.net/2019/11/14/205264ae9e6f4d579e73321c7c128131.png?imageView&thumbnail=200y140",
            "url":"https://tech.163.com/19/1114/11/ETUICNKC00097U7T.html"
        },
        {
            "ctime":"2019-11-14 09:58",
            "title":"大疆：只要有智能手机，就能跟踪附近的无人机",
            "description":"网易IT",
            "picUrl":"http://cms-bucket.ws.126.net/2019/11/14/472cf9a794ee4f99bce4b83fcbc83762.png?imageView&thumbnail=200y140",
            "url":"https://tech.163.com/19/1114/09/ETUEG4LE00097U7T.html"
        },
        {
            "ctime":"2019-11-14 08:31",
            "title":"微软最高职位华人沈向洋离职 他的成就有多大",
            "description":"网易IT",
            "picUrl":"http://cms-bucket.ws.126.net/2019/11/14/3c3df98ff33d4f9fae12d8526c5882a3.png?imageView&thumbnail=200y140",
            "url":"https://tech.163.com/19/1114/08/ETU9GQ2K00097U7T.html"
        },
        {
            "ctime":"2019-11-14 07:10",
            "title":"微软级别最高的中国员工沈向洋离职 继续任盖茨",
            "description":"网易IT",
            "picUrl":"http://cms-bucket.ws.126.net/2019/11/14/df26a978455c496aad9b3af25eee67b8.png?imageView&thumbnail=200y140",
            "url":"https://tech.163.com/19/1114/07/ETU4TTH000097U7T.html"
        },
        {
            "ctime":"2019-11-14 07:20",
            "title":"沈向洋致员工公开信：是时候去开启一个新的篇章",
            "description":"网易IT",
            "picUrl":"http://cms-bucket.ws.126.net/2019/11/14/8e1cc0abbd7843d7b43e35f737b1ae18.png?imageView&thumbnail=200y140",
            "url":"https://tech.163.com/19/1114/07/ETU5FJ3R00097U7T.html"
        },
        {
            "ctime":"2019-11-13 19:07",
            "title":"特斯拉国产在即，中国市场成关键",
            "description":"网易IT",
            "picUrl":"http://cms-bucket.ws.126.net/2019/11/13/cf9922fbac344551a5d22c4caaf65a8c.png?imageView&thumbnail=200y140",
            "url":"https://tech.163.com/19/1113/19/ETSRGBT600097U7T.html"
        },
        {
            "ctime":"2019-11-13 19:12",
            "title":"海康威视董事遭调查，回应称不是针对公司",
            "description":"网易IT",
            "picUrl":"http://cms-bucket.ws.126.net/2019/11/13/0654235e2cee45179529617230a970a8.jpeg?imageView&thumbnail=200y140",
            "url":"https://tech.163.com/19/1113/19/ETSRQ0RM00097U7T.html"
        }
    ]
}
